fawkes/__init__.py
fawkes/__main__.py
fawkes/align_face.py
fawkes/differentiator.py
fawkes/differentiator_lowkey.py
fawkes/master.py
fawkes/protection.py
fawkes/utils.py
fawkes-1.0.4.dist-info/LICENSE
fawkes-1.0.4.dist-info/METADATA
fawkes-1.0.4.dist-info/WHEEL
fawkes-1.0.4.dist-info/entry_points.txt
fawkes-1.0.4.dist-info/top_level.txt
fawkes-1.0.4.dist-info/RECORD
