Metadata-Version: 2.1
Name: fawkes
Version: 1.0.4
Summary: An utility to protect user privacy
Home-page: https://github.com/Shawn-Shan/fawkes
Author: Shawn Shan
Author-email: shawnshan@cs.uchicago.edu
License: BSD
Keywords: fawkes privacy ML
Platform: UNKNOWN
Classifier: Development Status :: 3 - Alpha
Classifier: License :: OSI Approved :: MIT License
Classifier: Operating System :: OS Independent
Classifier: Programming Language :: Python :: 3
Classifier: Topic :: System :: Monitoring
Requires-Python: >=3.5
Requires-Dist: numpy (>=1.19.5)
Requires-Dist: tensorflow (==2.4.1)
Requires-Dist: keras (==2.4.3)
Requires-Dist: mtcnn
Requires-Dist: pillow (>=7.0.0)
Requires-Dist: bleach (>=2.1.0)
